example_package/__init__.py
example_package/main.py
example_package_demo-0.1.0.dist-info/METADATA
example_package_demo-0.1.0.dist-info/WHEEL
example_package_demo-0.1.0.dist-info/licenses/LICENSE
example_package_demo-0.1.0.dist-info/RECORD
