Metadata-Version: 2.4
Name: example-package-demo
Version: 0.1.0
Summary: 一个简单的 Python 包示例，用于演示如何发布到 PyPI
Project-URL: Homepage, https://github.com/example/example-package
Project-URL: Repository, https://github.com/example/example-package
Project-URL: Issues, https://github.com/example/example-package/issues
Author-email: Example Author <example@example.com>
License: MIT
License-File: LICENSE
Classifier: Development Status :: 3 - Alpha
Classifier: Intended Audience :: Developers
Classifier: License :: OSI Approved :: MIT License
Classifier: Programming Language :: Python :: 3
Classifier: Programming Language :: Python :: 3.9
Classifier: Programming Language :: Python :: 3.10
Classifier: Programming Language :: Python :: 3.11
Classifier: Programming Language :: Python :: 3.12
Requires-Python: >=3.9
